LICENSE
MANIFEST.in
README.md
README_pypi.md
setup.py
src/ea/VERSION
src/ea/__init__.py
src/ea/releasenotes.txt
src/ea/server.py
src/ea/settings.ini
src/ea/test.ini
src/ea/libs/Logger.py
src/ea/libs/Scheduler.py
src/ea/libs/Settings.py
src/ea/libs/__init__.py
src/ea/libs/daemon.py
src/ea/libs/FileModels/GenericModel.py
src/ea/libs/FileModels/TestConfig.py
src/ea/libs/FileModels/TestData.py
src/ea/libs/FileModels/TestPlan.py
src/ea/libs/FileModels/TestResult.py
src/ea/libs/FileModels/TestSuite.py
src/ea/libs/FileModels/TestUnit.py
src/ea/libs/FileModels/__init__.py
src/ea/libs/NetLayerLib/ClientAgent.py
src/ea/libs/NetLayerLib/FifoCallBack.py
src/ea/libs/NetLayerLib/Messages.py
src/ea/libs/NetLayerLib/ServerAgent.py
src/ea/libs/NetLayerLib/TcpClient.py
src/ea/libs/NetLayerLib/TcpServer.py
src/ea/libs/NetLayerLib/TransactionManager.py
src/ea/libs/NetLayerLib/WebSocket.py
src/ea/libs/NetLayerLib/__init__.py
src/ea/libs/PyXmlDict/Dict2Xml.py
src/ea/libs/PyXmlDict/Test.py
src/ea/libs/PyXmlDict/Xml2Dict.py
src/ea/libs/PyXmlDict/__init__.py
src/ea/scripts/__init__.py
src/ea/scripts/certificate/ca.crt
src/ea/scripts/certificate/ca.key
src/ea/scripts/certificate/generate-ca-certifcate.sh
src/ea/scripts/certificate/generate-key.sh
src/ea/scripts/crontab/cron.cleanup-locks
src/ea/scripts/crontab/cron.cleanup-testsresult
src/ea/scripts/database/common_bdd.py
src/ea/scripts/database/create_database.py
src/ea/scripts/database/data_globals.json
src/ea/scripts/database/data_projects.json
src/ea/scripts/database/data_users.json
src/ea/scripts/database/init_data.py
src/ea/scripts/database/init_sqlite3.py
src/ea/scripts/helps/DocInspect.py
src/ea/scripts/helps/generate_helps.py
src/ea/scripts/iptables/iptables.rules
src/ea/scripts/reverseproxy/extensiveautomation_api.conf
src/ea/scripts/startup/svr.centos7
src/ea/scripts/startup/svr.centos8
src/ea/scripts/swagger/admin_restapi.yaml
src/ea/scripts/swagger/common_restapi.yaml
src/ea/scripts/swagger/generate_yaml.py
src/extensiveautomation_server.egg-info/PKG-INFO
src/extensiveautomation_server.egg-info/SOURCES.txt
src/extensiveautomation_server.egg-info/dependency_links.txt
src/extensiveautomation_server.egg-info/entry_points.txt
src/extensiveautomation_server.egg-info/requires.txt
src/extensiveautomation_server.egg-info/top_level.txt