Metadata-Version: 2.1
Name: extensiveautomation-server
Version: 22.3.0
Summary: Open source automation framework
Home-page: https://www.extensiveautomation.org/
Author: Denis MACHARD
Author-email: d.machard@gmail.com
Keywords: extensiveautomation automation testautomation testing
Platform: any
Classifier: License :: OSI Approved :: MIT License
Classifier: Programming Language :: Python :: 3
Classifier: Operating System :: OS Independent
Classifier: Topic :: Software Development :: Testing
Classifier: Topic :: Software Development :: Testing :: Acceptance
License-File: LICENSE
